containerpilot/__init__.py
containerpilot/containerpilot.py
containerpilot-0.0.1.dist-info/LICENSE
containerpilot-0.0.1.dist-info/METADATA
containerpilot-0.0.1.dist-info/WHEEL
containerpilot-0.0.1.dist-info/top_level.txt
containerpilot-0.0.1.dist-info/RECORD
